magicbot/__init__.py
magicbot/inject.py
magicbot/magic_reset.py
magicbot/magic_reset.pyi
magicbot/magic_tunable.py
magicbot/magicbot_tests.py
magicbot/magiccomponent.py
magicbot/magicrobot.py
magicbot/py.typed
magicbot/state_machine.py
robotpy_ext/__init__.py
robotpy_ext/version.py
robotpy_ext/autonomous/__init__.py
robotpy_ext/autonomous/selector.py
robotpy_ext/autonomous/selector_tests.py
robotpy_ext/autonomous/stateful_autonomous.py
robotpy_ext/common_drivers/README.rst
robotpy_ext/common_drivers/__init__.py
robotpy_ext/common_drivers/distance_sensors.py
robotpy_ext/common_drivers/distance_sensors_sim.py
robotpy_ext/common_drivers/driver_base.py
robotpy_ext/common_drivers/pressure_sensors.py
robotpy_ext/common_drivers/units.py
robotpy_ext/common_drivers/xl_max_sonar_ez.py
robotpy_ext/control/__init__.py
robotpy_ext/control/button_debouncer.py
robotpy_ext/control/toggle.py
robotpy_ext/misc/__init__.py
robotpy_ext/misc/annotations.py
robotpy_ext/misc/asyncio_policy.py
robotpy_ext/misc/crc7.py
robotpy_ext/misc/looptimer.py
robotpy_ext/misc/orderedclass.py
robotpy_ext/misc/periodic_filter.py
robotpy_ext/misc/precise_delay.py
robotpy_ext/misc/simple_watchdog.py
robotpy_wpilib_utilities-2025.1.0.dist-info/licenses/LICENSE
robotpy_wpilib_utilities-2025.1.0.dist-info/METADATA
robotpy_wpilib_utilities-2025.1.0.dist-info/WHEEL
robotpy_wpilib_utilities-2025.1.0.dist-info/top_level.txt
robotpy_wpilib_utilities-2025.1.0.dist-info/RECORD
