Metadata-Version: 2.4
Name: robotpy-wpilib-utilities
Version: 2025.1.0
Summary: Useful utility functions/objects for RobotPy
Home-page: https://github.com/robotpy/robotpy-wpilib-utilities
Author: RobotPy Development Team
Author-email: robotpy@googlegroups.com
License: BSD-3-Clause
Classifier: Development Status :: 5 - Production/Stable
Classifier: Intended Audience :: Developers
Classifier: License :: OSI Approved :: BSD License
Classifier: Operating System :: OS Independent
Classifier: Programming Language :: Python :: 3 :: Only
Classifier: Topic :: Software Development
Classifier: Topic :: Scientific/Engineering
Requires-Python: >=3.9
License-File: LICENSE
Requires-Dist: wpilib<2026,>=2025.1.1
Dynamic: license-file
